{
    "key": "group_59bbcd21c96cf",
    "title": "Surfguide",
    "fields": [
        {
            "key": "field_59bbcd21d46e8",
            "label": "Subtitle",
            "name": "subtitle",
            "type": "text",
            "instructions": "",
            "required": 0,
            "conditional_logic": 0,
            "wrapper": {
                "width": "",
                "class": "",
                "id": ""
            },
            "default_value": "",
            "placeholder": "",
            "prepend": "",
            "append": "",
            "maxlength": ""
        },
        {
            "key": "field_59bbcd21d46fb",
            "label": "Intro",
            "name": "intro",
            "type": "textarea",
            "instructions": "",
            "required": 0,
            "conditional_logic": 0,
            "wrapper": {
                "width": "",
                "class": "",
                "id": ""
            },
            "default_value": "",
            "placeholder": "",
            "maxlength": "",
            "rows": 2,
            "new_lines": "wpautop"
        },
        {
            "key": "field_59bbcd21d4709",
            "label": "Surfguide",
            "name": "surfguide",
            "type": "flexible_content",
            "instructions": "",
            "required": 0,
            "conditional_logic": 0,
            "wrapper": {
                "width": "",
                "class": "",
                "id": ""
            },
            "button_label": "Add Row",
            "min": "",
            "max": "",
            "layouts": [
                {
                    "key": "58f4a602e668a",
                    "name": "area",
                    "label": "Area Title",
                    "display": "row",
                    "sub_fields": [
                        {
                            "key": "field_59bbcd21db906",
                            "label": "title",
                            "name": "title",
                            "type": "text",
                            "instructions": "",
                            "required": "",
                            "conditional_logic": "",
                            "wrapper": {
                                "width": "",
                                "class": "",
                                "id": ""
                            },
                            "default_value": "",
                            "placeholder": "",
                            "prepend": "",
                            "append": "",
                            "maxlength": ""
                        }
                    ],
                    "min": "",
                    "max": ""
                },
                {
                    "key": "58f4a642e8758",
                    "name": "spot",
                    "label": "Spot",
                    "display": "row",
                    "sub_fields": [
                        {
                            "key": "field_59bbcd21db917",
                            "label": "Title",
                            "name": "title",
                            "type": "text",
                            "instructions": "",
                            "required": 0,
                            "conditional_logic": 0,
                            "wrapper": {
                                "width": "",
                                "class": "",
                                "id": ""
                            },
                            "default_value": "",
                            "placeholder": "",
                            "prepend": "",
                            "append": "",
                            "maxlength": ""
                        },
                        {
                            "key": "field_59bbcd21db924",
                            "label": "Image",
                            "name": "image",
                            "type": "image",
                            "instructions": "",
                            "required": 0,
                            "conditional_logic": 0,
                            "wrapper": {
                                "width": "",
                                "class": "",
                                "id": ""
                            },
                            "return_format": "array",
                            "preview_size": "medium",
                            "library": "all",
                            "min_width": "",
                            "min_height": "",
                            "min_size": "",
                            "max_width": "",
                            "max_height": "",
                            "max_size": "",
                            "mime_types": ""
                        },
                        {
                            "key": "field_59bbcd21db930",
                            "label": "Type",
                            "name": "type",
                            "type": "textarea",
                            "instructions": "",
                            "required": 0,
                            "conditional_logic": 0,
                            "wrapper": {
                                "width": "",
                                "class": "",
                                "id": ""
                            },
                            "default_value": "",
                            "placeholder": "",
                            "maxlength": "",
                            "rows": 2,
                            "new_lines": "wpautop"
                        },
                        {
                            "key": "field_59bbcd21db93c",
                            "label": "Conditions",
                            "name": "conditions",
                            "type": "textarea",
                            "instructions": "Works best with",
                            "required": 0,
                            "conditional_logic": 0,
                            "wrapper": {
                                "width": "",
                                "class": "",
                                "id": ""
                            },
                            "default_value": "",
                            "placeholder": "",
                            "maxlength": "",
                            "rows": 2,
                            "new_lines": "wpautop"
                        },
                        {
                            "key": "field_59bbcd21db948",
                            "label": "Crowd",
                            "name": "crowd",
                            "type": "textarea",
                            "instructions": "",
                            "required": 0,
                            "conditional_logic": 0,
                            "wrapper": {
                                "width": "",
                                "class": "",
                                "id": ""
                            },
                            "default_value": "",
                            "placeholder": "",
                            "maxlength": "",
                            "rows": 2,
                            "new_lines": "wpautop"
                        },
                        {
                            "key": "field_59bbcd21db954",
                            "label": "Info",
                            "name": "info",
                            "type": "textarea",
                            "instructions": "Extra Information",
                            "required": 0,
                            "conditional_logic": 0,
                            "wrapper": {
                                "width": "",
                                "class": "",
                                "id": ""
                            },
                            "default_value": "",
                            "placeholder": "",
                            "maxlength": "",
                            "rows": 2,
                            "new_lines": "wpautop"
                        }
                    ],
                    "min": "",
                    "max": ""
                }
            ]
        }
    ],
    "location": [
        [
            {
                "param": "page_template",
                "operator": "==",
                "value": "templates\/page-surfguide.php"
            }
        ]
    ],
    "menu_order": 0,
    "position": "normal",
    "style": "default",
    "label_placement": "top",
    "instruction_placement": "label",
    "hide_on_screen": [
        "the_content"
    ],
    "active": 1,
    "description": "",
    "modified": 1505479972
}