{
    "key": "group_59bbca78aa6e7",
    "title": "Home",
    "fields": [
        {
            "key": "field_59bbca78b72bc",
            "label": "Header Image",
            "name": "header_image",
            "type": "image",
            "instructions": "",
            "required": 0,
            "conditional_logic": 0,
            "wrapper": {
                "width": "",
                "class": "",
                "id": ""
            },
            "return_format": "array",
            "preview_size": "large",
            "library": "all",
            "min_width": 1920,
            "min_height": 1080,
            "min_size": "",
            "max_width": "",
            "max_height": "",
            "max_size": "",
            "mime_types": ""
        },
        {
            "key": "field_59bbca78b72ea",
            "label": "Intro",
            "name": "intro_text",
            "type": "textarea",
            "instructions": "",
            "required": 0,
            "conditional_logic": 0,
            "wrapper": {
                "width": "",
                "class": "",
                "id": ""
            },
            "default_value": "Olá Onda is a guesthouse for everyone who loves surfing, beautiful beaches, pastries, wine, nature and Portuguese culture. Because you’ll find all that. We are located in a quiet area of fishermen's town Ericeira, 10 minutes walking to the beach and downtown Ericeira. We offer spacious rooms with seaview and private balcony, as well as smaller, cozier rooms, all with private bathrooms.",
            "placeholder": "",
            "maxlength": "",
            "rows": "",
            "new_lines": "br"
        },
        {
            "key": "field_59bbca78b7309",
            "label": "Title - About Rooms",
            "name": "title_about_rooms",
            "type": "text",
            "instructions": "",
            "required": 0,
            "conditional_logic": 0,
            "wrapper": {
                "width": "",
                "class": "",
                "id": ""
            },
            "default_value": "Stay in our modern rooms",
            "placeholder": "",
            "prepend": "",
            "append": "",
            "maxlength": ""
        },
        {
            "key": "field_59bbca78b731b",
            "label": "Undertitle - About Rooms",
            "name": "undertitle_about_rooms",
            "type": "text",
            "instructions": "",
            "required": 0,
            "conditional_logic": 0,
            "wrapper": {
                "width": "",
                "class": "",
                "id": ""
            },
            "default_value": "",
            "placeholder": "",
            "prepend": "",
            "append": "",
            "maxlength": ""
        },
        {
            "key": "field_59bbca78b7327",
            "label": "Text - About Rooms",
            "name": "text_about_rooms",
            "type": "textarea",
            "instructions": "",
            "required": 0,
            "conditional_logic": 0,
            "wrapper": {
                "width": "",
                "class": "",
                "id": ""
            },
            "default_value": "Olá Onda Guesthouse is a typical Portuguese villa, renovated so it offers all you may need on your holiday. The house is surrounded by a big garden with different plants, cacti and fruit trees. There is an open air kitchen and free use of the wifi.",
            "placeholder": "",
            "maxlength": "",
            "rows": "",
            "new_lines": "br"
        },
        {
            "key": "field_59bbca78b7337",
            "label": "Title - Why",
            "name": "title_why",
            "type": "text",
            "instructions": "",
            "required": 0,
            "conditional_logic": 0,
            "wrapper": {
                "width": "",
                "class": "",
                "id": ""
            },
            "default_value": "WHY WOULD YOU STAY WITH US?",
            "placeholder": "",
            "prepend": "",
            "append": "",
            "maxlength": ""
        },
        {
            "key": "field_59bbca78b7343",
            "label": "Untertitle - Why",
            "name": "untertitle_why",
            "type": "text",
            "instructions": "",
            "required": 0,
            "conditional_logic": 0,
            "wrapper": {
                "width": "",
                "class": "",
                "id": ""
            },
            "default_value": "Reasons to stay at Olá Onda guest house",
            "placeholder": "",
            "prepend": "",
            "append": "",
            "maxlength": ""
        },
        {
            "key": "field_59bbca78b7354",
            "label": "Text - See The Ocean",
            "name": "text_see_the_ocean",
            "type": "textarea",
            "instructions": "",
            "required": 0,
            "conditional_logic": 0,
            "wrapper": {
                "width": "",
                "class": "",
                "id": ""
            },
            "default_value": "right after you wake up, and check out the stars in the quiet nights from your own balcony or bed",
            "placeholder": "",
            "maxlength": "",
            "rows": "",
            "new_lines": "br"
        },
        {
            "key": "field_59bbca78b737e",
            "label": "Testimonial 01",
            "name": "testimonial_01",
            "type": "textarea",
            "instructions": "",
            "required": 0,
            "conditional_logic": 0,
            "wrapper": {
                "width": "",
                "class": "",
                "id": ""
            },
            "default_value": "“This amazing place will open in the summer of 2017. I was lucky to visit the place while still under construction and it will definitely become a very nice guesthouse. Beachview from the hill, swimming pool, super friendly owners. Can't wait to go there again!”",
            "placeholder": "",
            "maxlength": "",
            "rows": 4,
            "new_lines": "br"
        },
        {
            "key": "field_59bbca78b738f",
            "label": "Testimonial 01 - Name",
            "name": "testimonial_01_name",
            "type": "textarea",
            "instructions": "",
            "required": 0,
            "conditional_logic": 0,
            "wrapper": {
                "width": "",
                "class": "",
                "id": ""
            },
            "default_value": "Folkert, 29",
            "placeholder": "",
            "maxlength": "",
            "rows": 2,
            "new_lines": "br"
        },
        {
            "key": "field_59bbca78b739b",
            "label": "Testimonial 02",
            "name": "testimonial_02",
            "type": "textarea",
            "instructions": "",
            "required": 0,
            "conditional_logic": 0,
            "wrapper": {
                "width": "",
                "class": "",
                "id": ""
            },
            "default_value": "“Fantastic location! The seaview is amazing and the city centre of Ericeira is within walking distance, so you're close to all the bars and restaurants. Lovely owners with a lot of knowledge from the area. They gave some great tips about the best places to surf, best beaches and where to go for dinner or coffee. I had a very pleasant stay and I would definitely return!”",
            "placeholder": "",
            "maxlength": "",
            "rows": 4,
            "new_lines": "br"
        },
        {
            "key": "field_59bbca78b73ab",
            "label": "Testimonial 02 - Name",
            "name": "testimonial_02_name",
            "type": "textarea",
            "instructions": "",
            "required": 0,
            "conditional_logic": 0,
            "wrapper": {
                "width": "",
                "class": "",
                "id": ""
            },
            "default_value": "Naima, 24",
            "placeholder": "",
            "maxlength": "",
            "rows": 2,
            "new_lines": "br"
        },
        {
            "key": "field_59bbca78b73b7",
            "label": "Title - Surf & Ericeira",
            "name": "title_surf_ericeira",
            "type": "text",
            "instructions": "",
            "required": 0,
            "conditional_logic": 0,
            "wrapper": {
                "width": "",
                "class": "",
                "id": ""
            },
            "default_value": "SURF & ERICEIRA",
            "placeholder": "",
            "prepend": "",
            "append": "",
            "maxlength": ""
        },
        {
            "key": "field_59bbca78b73c8",
            "label": "Underitle - Surf & Ericeira",
            "name": "undertitle_surf_ericeira",
            "type": "text",
            "instructions": "",
            "required": 0,
            "conditional_logic": 0,
            "wrapper": {
                "width": "",
                "class": "",
                "id": ""
            },
            "default_value": "Ericeira is the first World Surf Reserve in Europe",
            "placeholder": "",
            "prepend": "",
            "append": "",
            "maxlength": ""
        },
        {
            "key": "field_59bbca78b73e8",
            "label": "Text - Surf Ericeira",
            "name": "text_surf_ericeira",
            "type": "wysiwyg",
            "instructions": "",
            "required": 0,
            "conditional_logic": 0,
            "wrapper": {
                "width": "",
                "class": "",
                "id": ""
            },
            "default_value": "Part of the beautiful coastline of Ericeira, and therefore the surf spots, is protected area being Europe’s only World Surf Reserve. The coast is littered with golden sand beaches, stunning cliffs and great waves for everyone; beginners, intermediates and advanced surfers. Next to that, the town of Ericeira is a most pleasant place to stay. You’ll find tiny blue and white houses, small cobblestone streets, sunny terraces and friendly people. All a stone’s throw away from the beautiful city of Lisbon, Sintra and Cascais. Read more on where to surf in our Ericeira Surf Spot Guide (link)",
            "tabs": "all",
            "toolbar": "basic",
            "media_upload": 0,
            "delay": 0
        }
    ],
    "location": [
        [
            {
                "param": "page_template",
                "operator": "==",
                "value": "templates\/page-home.php"
            }
        ]
    ],
    "menu_order": 0,
    "position": "normal",
    "style": "default",
    "label_placement": "top",
    "instruction_placement": "label",
    "hide_on_screen": [
        "the_content"
    ],
    "active": 1,
    "description": "",
    "modified": 1505479292
}